{
  "type": "Feature",
  "properties": {
    "gn:admin1_code":"0.0",
    "gn:asciiname":"South District",
    "gn:country_code":"TC",
    "gn:dem":6,
    "gn:feature_class":"P",
    "gn:feature_code":"PPL",
    "gn:name":"South District",
    "gn:population":0,
    "gn:timezone":"America/Grand_Turk",
    "iso:country":"TC",
    "wof:name":"South District",
    "wof:placetype":"locality"
},
  "geometry": {"coordinates":[-71.21337,21.31906],"type":"Point"}
}