{
  "type": "Feature",
  "properties": {
    "gn:country":"TC",
    "gn:fcode":"PPL",
    "gn:population":751,
    "iso:country":"TC",
    "name:ceb_x_preferred":[
        "Cockburn Harbour"
    ],
    "name:eng_x_preferred":[
        "Cockburn Harbour"
    ],
    "name:fra_x_preferred":[
        "Cockburn Harbour"
    ],
    "name:nld_x_preferred":[
        "Cockburn Harbour"
    ],
    "qs:name":"Cockburn Harbour",
    "qs:photos_9r":0,
    "qs:photos_sr":0,
    "qs:pop_sr":"2",
    "wd:wordcount":75,
    "wof:name":"Cockburn Harbour",
    "wof:placetype":"locality",
    "wof:population":751
},
  "geometry": {"coordinates":[-71.53333000000001,21.48333],"type":"Point"}
}