{
  "type": "Feature",
  "properties": {
    "gn:admin1_code":"0.0",
    "gn:asciiname":"Lorimers",
    "gn:country_code":"TC",
    "gn:dem":14,
    "gn:feature_class":"P",
    "gn:feature_code":"PPL",
    "gn:name":"Lorimers",
    "gn:population":0,
    "gn:timezone":"America/Grand_Turk",
    "iso:country":"TC",
    "name:cat_x_preferred":[
        "Lorimers"
    ],
    "wof:name":"Lorimers",
    "wof:placetype":"locality"
},
  "geometry": {"coordinates":[-71.68729999999999,21.7954],"type":"Point"}
}